{"year": {"labels": ["January", "February", "March", "April", "May", "June", "July", "August", "September", "October", "November", "December"], "closed": [527, 311, 275, 167, 295, 306, 269, 205, 75, 143, 176, 243], "opened": [636, 404, 404, 278, 387, 387, 357, 263, 102, 215, 357, 416]}, "month": {"labels": ["Dec 4 - Dec 10", "Dec 11 - Dec 17", "Dec 18 - Dec 24", "Dec 25 - Dec 31"], "closed": [85, 60, 40, 3], "opened": [129, 101, 100, 14]}, "week": {"labels": ["Thursday", "Friday", "Saturday", "Sunday", "Monday", "Tuesday", "Wednesday"], "closed": [8, 3, 0, 2, 1, 2, 0], "opened": [15, 13, 8, 6, 7, 6, 1]}}